qcodeplot3d/__init__.py
qcodeplot3d/__main__.py
qcodeplot3d/gui.py
qcodeplot3d/py.typed
qcodeplot3d/cc_2d/__init__.py
qcodeplot3d/cc_2d/construction.py
qcodeplot3d/cc_2d/plotter.py
qcodeplot3d/cc_3d/__init__.py
qcodeplot3d/cc_3d/construction.py
qcodeplot3d/cc_3d/plotter.py
qcodeplot3d/common/__init__.py
qcodeplot3d/common/construction.py
qcodeplot3d/common/graph.py
qcodeplot3d/common/plotter.py
qcodeplot3d/common/stabilizers.py
qcodeplot3d-0.1.0.dist-info/licenses/LICENSE
qcodeplot3d-0.1.0.dist-info/METADATA
qcodeplot3d-0.1.0.dist-info/WHEEL
qcodeplot3d-0.1.0.dist-info/top_level.txt
qcodeplot3d-0.1.0.dist-info/RECORD
