Metadata-Version: 2.4
Name: qCodePlot3D
Version: 0.1.0
Summary: Create 3D visualizations of 3D quantum color codes.
Author-email: Lars Esser <mail@lars-esser.de>
License-Expression: MIT
Project-URL: Homepage, https://github.com/larsesser/qcodeplot3d
Project-URL: Issues, https://github.com/larsesser/qcodeplot3d/issues
Keywords: color code,3D,visualization,2D
Classifier: Intended Audience :: Science/Research
Classifier: Operating System :: OS Independent
Classifier: Programming Language :: Python :: 3
Classifier: Topic :: Multimedia :: Graphics :: 3D Rendering
Classifier: Topic :: Scientific/Engineering :: Physics
Classifier: Topic :: Scientific/Engineering :: Quantum Computing
Classifier: Topic :: Scientific/Engineering :: Visualization
Classifier: Typing :: Typed
Requires-Python: >=3.9
License-File: LICENSE
Requires-Dist: matplotlib
Requires-Dist: numpy
Requires-Dist: psutil
Requires-Dist: python-sat
Requires-Dist: pyvista>=0.44.2
Requires-Dist: rustworkx>=0.16.0
Requires-Dist: scipy
Provides-Extra: dev
Requires-Dist: ruff~=0.11.7; extra == "dev"
Dynamic: license-file
